advanced_plot/__init__.py
advanced_plot/hist.py
advanced_plot/stack_vertical_bar.py
advanced_plot/vertical_bar.py
advanced_plot-0.1.2.dist-info/LICENSE
advanced_plot-0.1.2.dist-info/WHEEL
advanced_plot-0.1.2.dist-info/METADATA
advanced_plot-0.1.2.dist-info/RECORD
